{"0":"limited edition alpha","1":"limited edition beta","2":"unlimited edition","3":"arabian nights","4":"dragon con","5":"harperprism book promos","6":"antiquities","7":"revised edition","8":"legends","9":"summer magic / edgar","10":"the dark","11":"fallen empires","12":"dci legend membership","13":"magazine inserts","14":"fourth edition","15":"foreign black border","16":"ice age","17":"chronicles","18":"renaissance","19":"rinascimento","20":"homelands","21":"alliances","22":"rivals quick start set","23":"arena league 1996","24":"redemption program","25":"mirage","26":"multiverse gift box","27":"introductory two-player set","28":"visions","29":"fifth edition","30":"portal","31":"portal demo game","32":"vanguard series","33":"weatherlight","34":"prerelease events","35":"tempest","36":"judge gift cards 1998","37":"stronghold","38":"portal second age","39":"exodus","40":"asia pacific land program","41":"urza's saga","42":"anthologies","43":"judge gift cards 1999","44":"arena league 1999","45":"urza's legacy","46":"classic sixth edition","47":"portal three kingdoms","48":"urza's destiny","49":"starter 1999","50":"guru","51":"worlds","52":"wizards of the coast online store","53":"mercadian masques","54":"battle royale box set","55":"junior super series","56":"friday night magic 2000","57":"judge gift cards 2000","58":"arena league 2000","59":"european land program","60":"nemesis","61":"starter 2000","62":"prophecy","63":"beatdown box set","64":"invasion","65":"friday night magic 2001","66":"judge gift cards 2001","67":"magic player rewards 2001","68":"arena league 2001","69":"planeshift","70":"seventh edition","71":"apocalypse","72":"odyssey","73":"deckmasters","74":"friday night magic 2002","75":"judge gift cards 2002","76":"arena league 2002","77":"magic player rewards 2002","78":"torment","79":"judgment","80":"magic online promos","81":"onslaught","82":"friday night magic 2003","83":"judge gift cards 2003","84":"magic player rewards 2003","85":"arena league 2003","86":"japan junior tournament","87":"magic online avatars","88":"legions","89":"scourge","90":"release events","91":"eighth edition","92":"mirrodin","93":"friday night magic 2004","94":"judge gift cards 2004","95":"magic player rewards 2004","96":"arena league 2004","97":"darksteel","98":"fifth dawn","99":"champions of kamigawa","100":"friday night magic 2005","101":"judge gift cards 2005","102":"magic player rewards 2005","103":"arena league 2005","104":"junior series europe","105":"magic premiere shop 2005","106":"betrayers of kamigawa","107":"saviors of kamigawa","108":"ninth edition","109":"salvat 2005","110":"ravnica: city of guilds","111":"two-headed giant tournament","112":"friday night magic 2006","113":"judge gift cards 2006","114":"magic player rewards 2006","115":"arena league 2006","116":"gateway 2006","117":"hachette uk","118":"junior apac series","119":"magic premiere shop 2006","120":"guildpact","121":"champs and states","122":"dissension","123":"coldsnap","124":"coldsnap theme decks","125":"time spiral timeshifted","126":"time spiral","127":"friday night magic 2007","128":"judge gift cards 2007","129":"magic player rewards 2007","130":"gateway 2007","131":"magic premiere shop 2007","132":"resale promos","133":"planar chaos","134":"pro tour promos","135":"grand prix promos","136":"future sight","137":"tenth edition","138":"tenth edition promos","139":"summer of magic","140":"masters edition","141":"lorwyn","142":"duel decks: elves vs. goblins","143":"friday night magic 2008","144":"judge gift cards 2008","145":"magic player rewards 2008","146":"gateway 2008","147":"magic premiere shop 2008","148":"morningtide","149":"launch parties","150":"15th anniversary cards","151":"shadowmoor","152":"eventide","153":"from the vault: dragons","154":"masters edition ii","155":"wizards play network 2008","156":"shards of alara","157":"duel decks: jace vs. chandra","158":"friday night magic 2009","159":"judge gift cards 2009","160":"magic player rewards 2009","161":"duels of the planeswalkers promos 2009","162":"magic premiere shop 2009","163":"wizards play network 2009","164":"miscellaneous book promos","165":"conflux","166":"url/convention promos","167":"duel decks: divine vs. demonic","168":"alara reborn","169":"magic 2010 promos","170":"magic 2010","171":"from the vault: exiled","172":"planechase","173":"planechase planes","174":"promotional planes","175":"masters edition iii","176":"zendikar promos","177":"zendikar","178":"duel decks: garruk vs. liliana","179":"premium deck series: slivers","180":"friday night magic 2010","181":"judge gift cards 2010","182":"magic player rewards 2010","183":"duels of the planeswalkers promos 2010","184":"magic premiere shop 2010","185":"wizards play network 2010","186":"worldwake promos","187":"worldwake","188":"duel decks: phyrexia vs. the coalition","189":"rise of the eldrazi promos","190":"rise of the eldrazi","191":"duels of the planeswalkers","192":"archenemy","193":"archenemy schemes","194":"promotional schemes","195":"magic 2011 promos","196":"magic 2011","197":"from the vault: relics","198":"duel decks: elspeth vs. tezzeret","199":"scars of mirrodin promos","200":"scars of mirrodin","201":"magic online theme decks","202":"premium deck series: fire and lightning","203":"duel decks: jace vs. chandra japanese promos","204":"friday night magic 2011","205":"judge gift cards 2011","206":"magic player rewards 2011","207":"duels of the planeswalkers promos 2011","208":"magic premiere shop 2011","209":"salvat 2011","210":"wizards play network 2011","211":"masters edition iv","212":"mirrodin besieged promos","213":"mirrodin besieged","214":"duel decks: knights vs. dragons","215":"new phyrexia promos","216":"new phyrexia","217":"duel decks: mirrodin pure vs. new phyrexia","218":"commander 2011","219":"magic 2012 promos","220":"magic 2012","221":"from the vault: legends","222":"duel decks: ajani vs. nicol bolas","223":"innistrad promos","224":"innistrad","225":"premium deck series: graveborn","226":"friday night magic 2012","227":"judge gift cards 2012","228":"league tokens 2012","229":"duels of the planeswalkers promos 2012","230":"idw comics 2012","231":"wizards play network 2012","232":"dark ascension promos","233":"dark ascension","234":"duel decks: venser vs. koth","235":"avacyn restored promos","236":"avacyn restored","237":"planechase 2012 planes","238":"planechase 2012","239":"magic 2013 promos","240":"magic 2013","241":"from the vault: realms","242":"duel decks: izzet vs. golgari","243":"return to ravnica promos","244":"return to ravnica","245":"commander's arsenal","246":"friday night magic 2013","247":"judge gift cards 2013","248":"league tokens 2013","249":"duels of the planeswalkers promos 2013","250":"idw comics 2013","251":"gatecrash promos","252":"gatecrash","253":"duel decks: sorin vs. tibalt","254":"world magic cup qualifiers","255":"dragon's maze promos","256":"dragon's maze","257":"modern masters","258":"magic 2014 promos","259":"san diego comic-con 2013","260":"magic 2014","261":"from the vault: twenty","262":"duel decks: heroes vs. monsters","263":"theros promos","264":"theros hero's path","265":"theros","266":"face the hydra","267":"commander 2013","268":"friday night magic 2014","269":"judge gift cards 2014","270":"league tokens 2014","271":"duels of the planeswalkers promos 2014","272":"idw comics 2014","273":"born of the gods promos","274":"born of the gods","275":"born of the gods hero's path","276":"battle the horde","277":"duel decks: jace vs. vraska","278":"journey into nyx promos","279":"journey into nyx","280":"journey into nyx hero's path","281":"defeat a god","282":"modern event deck 2014","283":"conspiracy","284":"vintage masters","285":"san diego comic-con 2014","286":"magic 2015 promos","287":"magic 2015 clash pack","288":"magic 2015","289":"from the vault: annihilation","290":"duel decks: speed vs. cunning","291":"khans of tarkir promos","292":"khans of tarkir","293":"commander 2014","294":"duel decks anthology: divine vs. demonic","295":"duel decks anthology: elves vs. goblins","296":"duel decks anthology: garruk vs. liliana","297":"duel decks anthology: jace vs. chandra","298":"friday night magic 2015","299":"judge gift cards 2015","300":"league tokens 2015","301":"ugin's fate","302":"fate reforged promos","303":"fate reforged","304":"fate reforged clash pack","305":"duel decks: elspeth vs. kiora","306":"dragons of tarkir promos","307":"dragons of tarkir","308":"tarkir dragonfury","309":"tempest remastered","310":"modern masters 2015","311":"san diego comic-con 2015","312":"magic origins clash pack","313":"magic origins","314":"magic origins promos","315":"from the vault: angels","316":"duel decks: zendikar vs. eldrazi","317":"battle for zendikar","318":"zendikar expeditions","319":"battle for zendikar promos","320":"bfz standard series","321":"commander 2015","322":"legendary cube","323":"friday night magic 2016","324":"judge gift cards 2016","325":"league tokens 2016","326":"oath of the gatewatch","327":"oath of the gatewatch promos","328":"duel decks: blessed vs. cursed","329":"shadows over innistrad promos","330":"shadows over innistrad","331":"welcome deck 2016","332":"eternal masters","333":"eldritch moon","334":"eldritch moon promos","335":"from the vault: lore","336":"conspiracy: take the crown","337":"duel decks: nissa vs. ob nixilis","338":"kaladesh","339":"kaladesh inventions","340":"kaladesh promos","341":"san diego comic-con 2016","342":"commander 2016","343":"you make the cube","344":"planechase anthology","345":"friday night magic 2017","346":"judge gift cards 2017","347":"league tokens 2017","348":"aether revolt promos","349":"aether revolt","350":"modern masters 2017","351":"duel decks: mind vs. might","352":"welcome deck 2017","353":"amonkhet","354":"amonkhet invocations","355":"amonkhet promos","356":"commander anthology","357":"archenemy: nicol bolas","358":"hour of devastation","359":"hour of devastation promos","360":"san diego comic-con 2017","361":"commander 2017","362":"xln standard showdown","363":"ixalan promos","364":"ixalan","365":"2017 gift pack","366":"duel decks: merfolk vs. goblins","367":"unstable promos","368":"iconic masters","369":"explorers of ixalan","370":"xln treasure chest","371":"from the vault: transform","372":"friday night magic 2018","373":"judge gift cards 2018","374":"rivals of ixalan promos","375":"rivals of ixalan","376":"nationals promos","377":"2018 lunar new year","378":"masters 25","379":"duel decks: elves vs. inventors","380":"dominaria","381":"dominaria promos","382":"battlebond","383":"commander anthology volume ii","384":"battlebond promos","385":"signature spellbook: jace","386":"global series jiang yanggu & mu yanling","387":"core set 2019","388":"core set 2019 promos","389":"m19 standard showdown","390":"arena new player experience","391":"san diego comic-con 2018","392":"commander 2018","393":"guilds of ravnica","394":"mythic edition","395":"guilds of ravnica promos","396":"grn ravnica weekend","397":"grn guild kit","398":"m19 gift pack","399":"game night","400":"ultimate box topper","401":"ultimate masters","402":"archenemy: nicol bolas schemes","403":"planechase anthology planes","404":"magicfest 2019","405":"ravnica allegiance promos","406":"ravnica allegiance","407":"rna guild kit","408":"rna ravnica weekend"}
